rana_process_sdk/__init__.py
rana_process_sdk/application/__init__.py
rana_process_sdk/application/local_test_rana_context.py
rana_process_sdk/application/prefect_rana_context.py
rana_process_sdk/application/rana_context.py
rana_process_sdk/application/rana_flow.py
rana_process_sdk/application/types/__init__.py
rana_process_sdk/application/types/dataset.py
rana_process_sdk/application/types/geojson.py
rana_process_sdk/application/types/path.py
rana_process_sdk/application/widgets/__init__.py
rana_process_sdk/application/widgets/base.py
rana_process_sdk/application/widgets/cell_size.py
rana_process_sdk/application/widgets/dataset.py
rana_process_sdk/application/widgets/file_picker.py
rana_process_sdk/application/widgets/tabs.py
rana_process_sdk/domain/__init__.py
rana_process_sdk/domain/dataset.py
rana_process_sdk/domain/exceptions.py
rana_process_sdk/domain/files.py
rana_process_sdk/domain/lizard_raster.py
rana_process_sdk/domain/lizard_task.py
rana_process_sdk/domain/personal_api_key.py
rana_process_sdk/domain/rana_process_parameters.py
rana_process_sdk/domain/types.py
rana_process_sdk/infrastructure/__init__.py
rana_process_sdk/infrastructure/api_exception.py
rana_process_sdk/infrastructure/api_provider.py
rana_process_sdk/infrastructure/json_schema.py
rana_process_sdk/infrastructure/lizard_api_provider.py
rana_process_sdk/infrastructure/lizard_raster_layer_gateway.py
rana_process_sdk/infrastructure/local_test_rana_runtime.py
rana_process_sdk/infrastructure/prefect_rana_runtime.py
rana_process_sdk/infrastructure/rana_api_provider.py
rana_process_sdk/infrastructure/rana_dataset_gateway.py
rana_process_sdk/infrastructure/rana_file_gateway.py
rana_process_sdk/infrastructure/rana_runtime.py
rana_process_sdk/infrastructure/rana_schematisation_gateway.py
rana_process_sdk/infrastructure/sentry_prefect_integration.py
rana_process_sdk/infrastructure/threedi_api_key_gateway.py
rana_process_sdk/presentation/__init__.py
rana_process_sdk/presentation/local_test.py
rana_process_sdk-0.10.dist-info/licenses/LICENSE
rana_process_sdk-0.10.dist-info/METADATA
rana_process_sdk-0.10.dist-info/WHEEL
rana_process_sdk-0.10.dist-info/top_level.txt
rana_process_sdk-0.10.dist-info/RECORD
