Metadata-Version: 2.4
Name: rana-process-sdk
Version: 0.10
Summary: The Software Development Kit for creating Rana processes.
Author-email: Nelen & Schuurmans <info@nelen-schuurmans.nl>
License-Expression: MIT
Project-URL: homepage, https://github.com/nens/rana-process-sdk
Classifier: Programming Language :: Python
Requires-Python: >=3.12
License-File: LICENSE
Requires-Dist: pydantic==2.9.*
Requires-Dist: pydantic-settings-yaml>=0.2
Requires-Dist: prefect==3.2.*
Requires-Dist: urllib3>=2
Requires-Dist: threedi-api-client>=4.1
Requires-Dist: sentry-sdk>=2.16
Dynamic: license-file
